clamming/__init__.py
clamming/claminfo.py
clamming/claminfomd.py
clamming/clamsclass.py
clamming/clamsmodules.py
clamming/clamspack.py
clamming/clamutils.py
clamming/classparser.py
clamming/exportoptions.py
clammingpy-2.1.dist-info/licenses/AUTHORS.md
clammingpy-2.1.dist-info/licenses/LICENSE.md
clammingpy-2.1.dist-info/METADATA
clammingpy-2.1.dist-info/WHEEL
clammingpy-2.1.dist-info/top_level.txt
clammingpy-2.1.dist-info/RECORD
