Metadata-Version: 2.4
Name: ClammingPy
Version: 2.1
Summary: Light Python-API Documentation in Markdown and accessible HTML
Author-email: Brigitte Bigi <contact@sppas.org>
Project-URL: Homepage, https://clamming.sf.net/
Keywords: python,class,module,documentation,doc,docstring,markdown,html,reST,epydoc
Classifier: Programming Language :: Python :: 3
Classifier: License :: OSI Approved :: GNU Affero General Public License v3 or later (AGPLv3+)
Classifier: Operating System :: OS Independent
Classifier: Topic :: Documentation
Classifier: Topic :: Software Development :: Documentation
Classifier: Intended Audience :: Developers
Classifier: Development Status :: 5 - Production/Stable
Requires-Python: >=3.9
License-File: LICENSE.md
License-File: AUTHORS.md
Requires-Dist: pygments
Requires-Dist: markdown2
Provides-Extra: dev
Requires-Dist: pylint~=2.14.0; extra == "dev"
Requires-Dist: toml~=0.10.2; extra == "dev"
Provides-Extra: tests
Requires-Dist: coverage~=7.3.0; extra == "tests"
Requires-Dist: python-dotenv~=1.0.0; extra == "tests"
Dynamic: license-file
